showimg.py
showimg-0.1.1.dist-info/DESCRIPTION.rst
showimg-0.1.1.dist-info/METADATA
showimg-0.1.1.dist-info/RECORD
showimg-0.1.1.dist-info/WHEEL
showimg-0.1.1.dist-info/entry_points.txt
showimg-0.1.1.dist-info/metadata.json
showimg-0.1.1.dist-info/top_level.txt
