Metadata-Version: 2.0
Name: showimg
Version: 0.1.1
Summary: Show image on 256-coloured terminal.
Home-page: https://github.com/kjwon15/showimg
Author: Kjwon15
Author-email: UNKNOWN
License: MIT
Platform: UNKNOWN
Requires-Dist: Pillow (>=4.0.0)
Requires-Dist: requests (>=2.12.5)
